{
	"recordList": [
		{
			"t": 1460448503910,
			"prizeinfo": "电子称",
			"prizid": 1,
			"prizename": "一等奖",
			"prizeimage": "images/p_0.jpg"
		},
		{
			"t": 1460448503910,
			"prizeinfo": "电子称",
			"prizid": 1,
			"prizename": "一等奖",
			"prizeimage": "images/p_0.jpg"
		},
		{
			"t": 1460448503910,
			"prizeinfo": "【“奔跑吧，宝贝”冰雪运动会】入场券1张",
			"prizid": 1,
			"prizename": "一等奖",
			"prizeimage": "images/p_0.jpg"
		}
	],
	
	"actioninfo": "<p><br/></p><p style=\"white-space: normal;\"><br/></p><p><strong>活动奖品：</strong></p><p>【“奔跑吧，宝贝”冰雪运动会】入场券</p><p><strong>抽奖提示：</strong><br/></p><p>仅限【“奔跑吧，宝贝”冰雪运动会】报名用户参与抽奖；</p><p>每人每天限 3 次抽奖机会，中奖用户请保持手机畅通；<br/></p><p><br/></p><p style=\"white-space: normal;\"><span style=\"color: rgb(255, 0, 0);\">特别提醒</span>：</p><p style=\"white-space: normal;\">1、本次活动报名火爆，<span style=\"color: rgb(255, 0, 0);\">只有报过名参加大转盘抽奖并且获得一等奖的车友，才能获得滑雪场免费门票，每辆车限5个免费名额，</span></p><p style=\"white-space: normal;\"><span style=\"color: rgb(255, 0, 0);\"><span style=\"color: rgb(0, 0, 0);\">2、所有免费入场的车友，每人都需自费10元购买滑雪保险。</span></span></p><p style=\"white-space: normal;\">3、应广大车友的要求，所有报过名，<span style=\"color: rgb(0, 176, 80);\"><strong>未中奖</strong></span>的车友，可以享受门票优惠:<span style=\"color: rgb(255, 0, 0);\">1月23日至1月31日，凭报名信息到郑州龙泉国际滑雪场享受以下优惠：周末原价168元,享受6.5折，优惠后110元；平时原价138元，享受5.8折，优惠后80元</span>。</p><p style=\"white-space: normal;\">4、以上优惠只针对本次报名的车友，不针对其它车友。</p><p style=\"white-space: normal;\">5、以上优惠不包含10元/人滑雪保险。</p><p style=\"white-space: normal;\">6、不管您是中奖车友，还是未中奖车友，滑雪前请自行缴纳滑雪押金200元/人（如无二次消费滑雪结束后退回押金）。</p><p style=\"white-space: normal;\">7、如有任何疑问：请拨打0371-65888659。</p><p style=\"white-space: normal;\"><img src=\"http://radio1.iwxlh.com/Radio/resource/d6c22c38bf3b497b9c5e083c942511cf\" title=\"\" alt=\"\"/></p><p style=\"white-space: normal;\"><img src=\"http://radio1.iwxlh.com/Radio/resource/c98cc06bfbd445a8898aa3cafa6c63a5\" title=\"\" alt=\"\"/></p><p style=\"white-space: normal;\"><br/></p><p style=\"white-space: normal;\"><span style=\"color: rgb(255, 0, 0);\"><strong><img src=\"http://radio1.iwxlh.com/Radio/resource/c88f5226a1234996ad8f9b52868768b0\" title=\"\" alt=\"\"/></strong></span></p><p style=\"white-space: normal;\"><span style=\"color: rgb(255, 0, 0);\"><strong><img src=\"http://radio1.iwxlh.com/Radio/resource/bb6ccc15f2fe4be59095d3a60d67840c\" title=\"\" alt=\"\"/></strong></span></p><p style=\"white-space: normal;\"><span style=\"color: rgb(255, 0, 0);\"><strong>抽中奖的朋友请扫码加入下面微信群，方便大家沟通，本活动将于2016年1月23日举行，所有获奖的朋友，我们将会一一通知，请大家耐心等待。</strong></span></p><p style=\"white-space: normal;\"><img src=\"http://radio1.iwxlh.com/Radio/resource/fe80191fce4a4db6b559a9d479f5333a\" title=\"\" alt=\"\"/></p><p><span style=\"font-size: 14px;\">本次活动最终解释权归河南交通广播所有</span></p>"
}